nlptkl/__init__.py
nlptkl/loader.py
nlptkl/data/sample1.txt
nlptkl/data/streamlitx.txt
nlptkl-0.1.0.dist-info/LICENSE
nlptkl-0.1.0.dist-info/METADATA
nlptkl-0.1.0.dist-info/WHEEL
nlptkl-0.1.0.dist-info/top_level.txt
nlptkl-0.1.0.dist-info/RECORD
